azure/core/__init__.py
azure/core/_azure_clouds.py
azure/core/_enum_meta.py
azure/core/_match_conditions.py
azure/core/_pipeline_client.py
azure/core/_pipeline_client_async.py
azure/core/_version.py
azure/core/async_paging.py
azure/core/configuration.py
azure/core/credentials.py
azure/core/credentials_async.py
azure/core/exceptions.py
azure/core/messaging.py
azure/core/paging.py
azure/core/py.typed
azure/core/serialization.py
azure/core/settings.py
azure/core/pipeline/__init__.py
azure/core/pipeline/_base.py
azure/core/pipeline/_base_async.py
azure/core/pipeline/_tools.py
azure/core/pipeline/_tools_async.py
azure/core/pipeline/policies/__init__.py
azure/core/pipeline/policies/_authentication.py
azure/core/pipeline/policies/_authentication_async.py
azure/core/pipeline/policies/_base.py
azure/core/pipeline/policies/_base_async.py
azure/core/pipeline/policies/_custom_hook.py
azure/core/pipeline/policies/_distributed_tracing.py
azure/core/pipeline/policies/_redirect.py
azure/core/pipeline/policies/_redirect_async.py
azure/core/pipeline/policies/_retry.py
azure/core/pipeline/policies/_retry_async.py
azure/core/pipeline/policies/_sensitive_header_cleanup_policy.py
azure/core/pipeline/policies/_universal.py
azure/core/pipeline/policies/_utils.py
azure/core/pipeline/transport/__init__.py
azure/core/pipeline/transport/_aiohttp.py
azure/core/pipeline/transport/_base.py
azure/core/pipeline/transport/_base_async.py
azure/core/pipeline/transport/_base_requests_async.py
azure/core/pipeline/transport/_bigger_block_size_http_adapters.py
azure/core/pipeline/transport/_requests_asyncio.py
azure/core/pipeline/transport/_requests_basic.py
azure/core/pipeline/transport/_requests_trio.py
azure/core/polling/__init__.py
azure/core/polling/_async_poller.py
azure/core/polling/_poller.py
azure/core/polling/async_base_polling.py
azure/core/polling/base_polling.py
azure/core/rest/__init__.py
azure/core/rest/_aiohttp.py
azure/core/rest/_helpers.py
azure/core/rest/_http_response_impl.py
azure_core-1.32.0.dist-info/LICENSE
azure_core-1.32.0.dist-info/METADATA
azure_core-1.32.0.dist-info/WHEEL
azure_core-1.32.0.dist-info/top_level.txt
azure_core-1.32.0.dist-info/RECORD
