Metadata-Version: 2.1
Name: azure-core
Version: 1.32.0
Summary: Microsoft Azure Core Library for Python
Home-page: https://github.com/Azure/azure-sdk-for-python/tree/main/sdk/core/azure-core
Author: Microsoft Corporation
Author-email: azpysdkhelp@microsoft.com
License: MIT License
Keywords: azure,azure sdk
Classifier: Development Status :: 5 - Production/Stable
Classifier: Programming Language :: Python
Classifier: Programming Language :: Python :: 3 :: Only
Classifier: Programming Language :: Python :: 3
Classifier: Programming Language :: Python :: 3.8
Classifier: Programming Language :: Python :: 3.9
Classifier: Programming Language :: Python :: 3.10
Classifier: Programming Language :: Python :: 3.11
Classifier: Programming Language :: Python :: 3.12
Classifier: License :: OSI Approved :: MIT License
Requires-Python: >=3.8
License-File: LICENSE
Requires-Dist: requests>=2.21.0
Requires-Dist: six>=1.11.0
Requires-Dist: typing-extensions>=4.6.0
Provides-Extra: aio
Requires-Dist: aiohttp>=3.0; extra == "aio"
